MANIFEST.in
README.rst
setup.cfg
setup.py
docs/conf.py
docs/index.rst
tastypie_client/__init__.py
tastypie_client/core.py
tastypie_client/exceptions.py
tastypie_client/serializers.py
tastypie_client.egg-info/PKG-INFO
tastypie_client.egg-info/SOURCES.txt
tastypie_client.egg-info/dependency_links.txt
tastypie_client.egg-info/requires.txt
tastypie_client.egg-info/top_level.txt