Metadata-Version: 1.0
Name: tastypie-client
Version: 0.1.0
Summary: Client for Django-Tastypie based REST services
Home-page: UNKNOWN
Author: Philippe Muller
Author-email: philippe.muller@cfm.fr
License: UNKNOWN
Keywords: tastypie rest django requests
Platform: UNKNOWN
Classifier: Development Status :: 3 - Alpha
Classifier: Intended Audience :: Developers
Classifier: Framework :: Django
Classifier: License :: OSI Approved :: BSD License
Classifier: Topic :: Software Development :: Libraries :: Python Modules
Classifier: Topic :: Internet :: WWW/HTTP
